mikecore/Dfs123File.py
mikecore/DfsBuilder.py
mikecore/DfsDLL.py
mikecore/DfsFactory.py
mikecore/DfsFile.py
mikecore/DfsFileFactory.py
mikecore/DfsuBuilder.py
mikecore/DfsuFile.py
mikecore/MeshBuilder.py
mikecore/MeshFile.py
mikecore/Projections.py
mikecore/__init__.py
mikecore/eum.py
mikecore/bin/linux/EUM.ubg
mikecore/bin/linux/EUM.xml
mikecore/bin/linux/EUM_Default_Units.ubg
mikecore/bin/linux/EUM_US_Units.ubg
mikecore/bin/linux/custom_projection.pfs
mikecore/bin/linux/ellipsoid.pfs
mikecore/bin/linux/libMzCart.so
mikecore/bin/linux/libcilkrts.so.5
mikecore/bin/linux/libeum.so
mikecore/bin/linux/libimf.so
mikecore/bin/linux/libintlc.so.5
mikecore/bin/linux/libiomp5.so
mikecore/bin/linux/libirng.so
mikecore/bin/linux/libpfs2004.so
mikecore/bin/linux/libsvml.so
mikecore/bin/linux/libufs.so
mikecore/bin/linux/libxerces-c-3.1.so
mikecore/bin/linux/map_projection.pfs
mikecore/bin/linux/state_plane_nad27.pfs
mikecore/bin/linux/state_plane_nad83.pfs
mikecore/bin/windows/DHIfl.dll
mikecore/bin/windows/EUM.ubg
mikecore/bin/windows/EUM.xml
mikecore/bin/windows/EUM_Default_Units.ubg
mikecore/bin/windows/EUM_US_Units.ubg
mikecore/bin/windows/MzCart.dll
mikecore/bin/windows/ams2004.dll
mikecore/bin/windows/amsT2004.dll
mikecore/bin/windows/ellipsoid.pfs
mikecore/bin/windows/eum.dll
mikecore/bin/windows/map_projection.pfs
mikecore/bin/windows/pfs2004.dll
mikecore/bin/windows/state_plane_nad27.pfs
mikecore/bin/windows/state_plane_nad83.pfs
mikecore/bin/windows/ufs.dll
miketools/Dfs0ToAscii.py
miketools/DfsShowInfo.py
miketools/__init__.py
tests/Test.py
tests/__init__.py
tests/examples_dfs0.py
tests/examples_dfs2.py
tests/examples_dfsu.py
tests/examples_misc.py
tests/test_dfs0.py
tests/test_dfs2.py
tests/test_dfs3.py
tests/test_dfs_basic.py
tests/test_dfs_custom_block.py
tests/test_dfs_spatial_axis.py
tests/test_dfs_static_item.py
tests/test_dfs_temporal_axis.py
tests/test_dfsbuilder.py
tests/test_dfsu2D.py
tests/test_dfsu_file.py
tests/test_eum.py
tests/test_mesh.py
mikecore-0.2.1.dist-info/LICENSE.txt
mikecore-0.2.1.dist-info/METADATA
mikecore-0.2.1.dist-info/WHEEL
mikecore-0.2.1.dist-info/top_level.txt
mikecore-0.2.1.dist-info/RECORD
