Metadata-Version: 2.1
Name: mikecore
Version: 0.2.1
Summary: MIKE Core contains core libraries, like DFS (Data File System), EUM and more.
Home-page: https://github.com/DHI/mikecore-python
Author: DHI
Author-email: mike@dhigroup.com
License: BSD-3
Platform: UNKNOWN
Classifier: License :: OSI Approved :: BSD License
Classifier: Programming Language :: Python :: 3
Requires-Python: >=3.5<
Requires-Dist: numpy
